.gitignore
bookshelf/__init__.py
bookshelf/bundle.py
bookshelf/commands/__init__.py
bookshelf/commands/docs.py
bookshelf/commands/examples.py
bookshelf/commands/modules.py
bookshelf/definitions.py
bookshelf/helpers.py
bookshelf/logger.py
bookshelf/metadata/__init__.py
bookshelf/metadata/feature.py
bookshelf/metadata/module.py
bookshelf/module.py
bookshelf/modules/@dev/README.md
bookshelf/modules/@dev/module.json
bookshelf/modules/@dev/pack.png
bookshelf/modules/@prefabs/README.md
bookshelf/modules/@prefabs/module.json
bookshelf/modules/@prefabs/pack.png
bookshelf/modules/@runtime/README.md
bookshelf/modules/@runtime/module.json
bookshelf/modules/@runtime/pack.png
bookshelf/modules/@suite/README.md
bookshelf/modules/@suite/module.json
bookshelf/modules/@suite/pack.png
bookshelf/modules/bs.bitwise/README.md
bookshelf/modules/bs.bitwise/data/bs.bitwise/function/__load__.mcfunction
bookshelf/modules/bs.bitwise/data/bs.bitwise/function/__unload__.mcfunction
bookshelf/modules/bs.bitwise/data/bs.bitwise/function/and/and.mcfunction
bookshelf/modules/bs.bitwise/data/bs.bitwise/function/and/compute.mcfunction
bookshelf/modules/bs.bitwise/data/bs.bitwise/function/bit_count.mcfunction
bookshelf/modules/bs.bitwise/data/bs.bitwise/function/bit_length/bit_length.mcfunction
bookshelf/modules/bs.bitwise/data/bs.bitwise/function/bit_length/group_1.mcfunction
bookshelf/modules/bs.bitwise/data/bs.bitwise/function/bit_length/group_2.mcfunction
bookshelf/modules/bs.bitwise/data/bs.bitwise/function/bit_length/group_3.mcfunction
bookshelf/modules/bs.bitwise/data/bs.bitwise/function/bit_length/group_4.mcfunction
bookshelf/modules/bs.bitwise/data/bs.bitwise/function/not.mcfunction
bookshelf/modules/bs.bitwise/data/bs.bitwise/function/or.mcfunction
bookshelf/modules/bs.bitwise/data/bs.bitwise/function/two_complement.mcfunction
bookshelf/modules/bs.bitwise/data/bs.bitwise/function/xor.mcfunction
bookshelf/modules/bs.bitwise/data/bs.bitwise/tags/function/and.json
mcbookshelf-3.0.2.dist-info/METADATA
mcbookshelf-3.0.2.dist-info/WHEEL
mcbookshelf-3.0.2.dist-info/entry_points.txt
mcbookshelf-3.0.2.dist-info/licenses/LICENSE
mcbookshelf-3.0.2.dist-info/RECORD
