Metadata-Version: 2.1
Name: mcbookshelf
Version: 3.0.2
Summary: Scripts for Bookshelf and the Github pipeline.
Author-Email: Bookshelf Contributors <contact@gunivers.net>
License: MPL-2.0
Requires-Python: >=3.12
Requires-Dist: beet>=0.110.0
Requires-Dist: click>=8.1.8
Requires-Dist: colorama>=0.4.6
Requires-Dist: pydantic>=2.11.3
Requires-Dist: requests>=2.32.3
Requires-Dist: lectern>=0.34.0
